CHANGELOG.md
LICENSE
MANIFEST.in
README.md
dev-requirements.txt
setup.py
aiopype/__init__.py
aiopype/flow.py
aiopype/manager.py
aiopype/processor.py
aiopype.egg-info/PKG-INFO
aiopype.egg-info/SOURCES.txt
aiopype.egg-info/dependency_links.txt
aiopype.egg-info/requires.txt
aiopype.egg-info/top_level.txt
aiopype/protocol/__init__.py
aiopype/protocol/async_protocol.py
aiopype/protocol/mixin.py
aiopype/protocol/sync_protocol.py
aiopype/sources/__init__.py
aiopype/sources/pusher.py
aiopype/sources/rest.py
aiopype/sources/schedulers.py
aiopype/sources/socketio.py
aiopype/sources/time.py
aiopype/sources/websocket.py
tests/test_flow.py
tests/test_manager.py
tests/test_processor.py
tests/__pycache__/test_flow.cpython-35.pyc
tests/__pycache__/test_manager.cpython-35.pyc
tests/__pycache__/test_processor.cpython-35.pyc
tests/sources/__init__.py
tests/sources/test_pusher.py
tests/sources/test_rest.py
tests/sources/test_scheduler.py
tests/sources/test_socketio.py
tests/sources/test_websocket.py
tests/sources/__pycache__/__init__.cpython-35.pyc
tests/sources/__pycache__/test_pusher.cpython-35.pyc
tests/sources/__pycache__/test_rest.cpython-35.pyc
tests/sources/__pycache__/test_scheduler.cpython-35.pyc
tests/sources/__pycache__/test_socketio.cpython-35.pyc
tests/sources/__pycache__/test_websocket.cpython-35.pyc