Metadata-Version: 1.0
Name: aiopype
Version: 0.1.4
Summary: AioPype - Flow based programming with asyncio
Home-page: https://www.github.com/uphold/aiopype/
Author: Jorge Alpedrinha Ramos
Author-email: python@uphold.com
License: LICENSE
Platform: UNKNOWN
